modular_intelligence/__init__.py
modular_intelligence/agents/__init__.py
modular_intelligence/agents/base.py
modular_intelligence/database/__init__.py
modular_intelligence/database/config.py
modular_intelligence/database/init_db.py
modular_intelligence/database/schema.sql
modular_intelligence/scripts/__init__.py
modular_intelligence/scripts/create_basic_bot.py
modular_intelligence/scripts/demo_script.py
modular_intelligence/scripts/list_tables.py
modular_intelligence/scripts/rebuild_db.py
modular_intelligence/scripts/conversations/convos_for_demo_script.py
modular_intelligence/stacks/__init__.py
modular_intelligence/stacks/stack.py
modular_intelligence/utils/__init__.py
modular_intelligence/utils/conversation_formatter.py
modular_intelligence/utils/prompts.py
modular_intelligence-0.0.11.dist-info/LICENSE
modular_intelligence-0.0.11.dist-info/METADATA
modular_intelligence-0.0.11.dist-info/WHEEL
modular_intelligence-0.0.11.dist-info/top_level.txt
modular_intelligence-0.0.11.dist-info/RECORD
