Metadata-Version: 2.1
Name: modular_intelligence
Version: 0.0.11
Summary: This repository contains an AI agent framework that was made to simplify and separate the building and deployment phases of AI agents.  Using sqlite, we are able to create & save agents, put them into stacks, then deploy those stacks of agents into any application connected to the server or machine.
Author-email: xrgpublic <xrgpublic@gmail.com>
Project-URL: Homepage, https://github.com/xrgpublic/modular-intelligence
Project-URL: Issues, https://github.com/xrgpublic/modular-intelligence/issues
Classifier: Programming Language :: Python :: 3
Classifier: License :: OSI Approved :: MIT License
Classifier: Operating System :: OS Independent
Requires-Python: >=3.12
License-File: LICENSE
Requires-Dist: colorama==0.4.6
Requires-Dist: ollama==0.4.4
Requires-Dist: pandas==2.2.3
Requires-Dist: tabulate==0.9.0
